dendroextractors/__init__.py
dendroextractors/_version.py
dendroextractors/nwb/__init__.py
dendroextractors/nwb/nwbdendroextractors.py
dendroextractors-0.1.9.dist-info/LICENSE
dendroextractors-0.1.9.dist-info/METADATA
dendroextractors-0.1.9.dist-info/WHEEL
dendroextractors-0.1.9.dist-info/RECORD
